toio/__init__.py
toio/coordinate_systems.py
toio/cube/__init__.py
toio/cube/api/__init__.py
toio/cube/api/base_class.py
toio/cube/api/battery.py
toio/cube/api/button.py
toio/cube/api/configuration.py
toio/cube/api/id_information.py
toio/cube/api/indicator.py
toio/cube/api/motor.py
toio/cube/api/sensor.py
toio/cube/api/sound.py
toio/device_interface/__init__.py
toio/device_interface/ble.py
toio/logger.py
toio/position.py
toio/scanner/__init__.py
toio/scanner/ble.py
toio/scanner/platform/windows_ble.py
toio/simple/__init__.py
toio/standard_id.py
toio/toio_uuid.py
toio/utility.py
toio_py-1.0.2.dist-info/LICENSE
toio_py-1.0.2.dist-info/WHEEL
toio_py-1.0.2.dist-info/METADATA
toio_py-1.0.2.dist-info/RECORD
