Metadata-Version: 2.1
Name: toio-py
Version: 1.0.2
Summary: Control toio™Core Cube
Home-page: https://toio.io/
License: MIT
Keywords: toio
Author: Sony Interactive Entertainment
Requires-Python: >=3.11,<4.0
Classifier: License :: OSI Approved :: MIT License
Classifier: Programming Language :: Python :: 3
Classifier: Programming Language :: Python :: 3.11
Requires-Dist: bleak (==0.20.1)
Project-URL: Repository, https://github.com/toio/toio.py
